togglcmder/__init__.py
togglcmder/__main__.py
togglcmder/version.py
togglcmder/test/__init__.py
togglcmder/test/test_caching.py
togglcmder/test/test_decoders.py
togglcmder/test/test_encoders.py
togglcmder/test/test_endpoints.py
togglcmder/test/test_filters.py
togglcmder/toggl/__init__.py
togglcmder/toggl/caching.py
togglcmder/toggl/commands.py
togglcmder/toggl/downloader.py
togglcmder/toggl/builders/__init__.py
togglcmder/toggl/builders/project_builder.py
togglcmder/toggl/builders/tag_builder.py
togglcmder/toggl/builders/time_entry_builder.py
togglcmder/toggl/builders/user_builder.py
togglcmder/toggl/builders/workspace_builder.py
togglcmder/toggl/cli/__init__.py
togglcmder/toggl/cli/helpers.py
togglcmder/toggl/cli/projects.py
togglcmder/toggl/cli/tags.py
togglcmder/toggl/cli/time_entries.py
togglcmder/toggl/cli/workspaces.py
togglcmder/toggl/decoders/__init__.py
togglcmder/toggl/decoders/project_decoder.py
togglcmder/toggl/decoders/tag_decoder.py
togglcmder/toggl/decoders/time_entry_decoder.py
togglcmder/toggl/decoders/user_decoder.py
togglcmder/toggl/decoders/workspace_decoder.py
togglcmder/toggl/encoders/__init__.py
togglcmder/toggl/encoders/project_encoder.py
togglcmder/toggl/encoders/tag_encoder.py
togglcmder/toggl/encoders/time_entry_encoder.py
togglcmder/toggl/endpoints/__init__.py
togglcmder/toggl/endpoints/api.py
togglcmder/toggl/endpoints/projects.py
togglcmder/toggl/endpoints/tags.py
togglcmder/toggl/endpoints/time_entries.py
togglcmder/toggl/endpoints/users.py
togglcmder/toggl/endpoints/workspaces.py
togglcmder/toggl/filters/__init__.py
togglcmder/toggl/filters/projects.py
togglcmder/toggl/filters/tags.py
togglcmder/toggl/filters/time_entries.py
togglcmder/toggl/filters/workspaces.py
togglcmder/toggl/types/__init__.py
togglcmder/toggl/types/project.py
togglcmder/toggl/types/tag.py
togglcmder/toggl/types/time_entry.py
togglcmder/toggl/types/user.py
togglcmder/toggl/types/workspace.py
togglcmder/toggl/views/__init__.py
togglcmder/toggl/views/project.py
togglcmder-2.0.6.dist-info/LICENSE
togglcmder-2.0.6.dist-info/METADATA
togglcmder-2.0.6.dist-info/WHEEL
togglcmder-2.0.6.dist-info/entry_points.txt
togglcmder-2.0.6.dist-info/top_level.txt
togglcmder-2.0.6.dist-info/RECORD
