Metadata-Version: 2.1
Name: togglcmder
Version: 2.0.6
Summary: Utility to control Toggl timers via the REST API.
Home-page: https://github.com/yatesjr/toggl-cmder
Author: Jonathan Yates
Author-email: yatesjr@avernakis.com
License: UNKNOWN
Platform: UNKNOWN
Classifier: Programming Language :: Python :: 3
Classifier: Operating System :: OS Independent
Requires-Python: >=3.6
Requires-Dist: attrs (>=19.3.0)
Requires-Dist: Automat (>=20.2.0)
Requires-Dist: certifi (>=2020.6.20)
Requires-Dist: chardet (>=3.0.4)
Requires-Dist: Click (>=7.1.2)
Requires-Dist: constantly (>=15.1.0)
Requires-Dist: hyperlink (>=19.0.0)
Requires-Dist: idna (>=2.10)
Requires-Dist: incremental (>=17.5.0)
Requires-Dist: PyHamcrest (>=2.0.2)
Requires-Dist: pytz (>=2020.1)
Requires-Dist: requests (>=2.24.0)
Requires-Dist: six (>=1.15.0)
Requires-Dist: tabulate (>=0.8.7)
Requires-Dist: Twisted (>=20.3.0)
Requires-Dist: tzlocal (>=2.1)
Requires-Dist: urllib3 (>=1.25.10)
Requires-Dist: zope.interface (>=5.1.0)
